getmyinvoices/__init__.py
getmyinvoices/client.py
getmyinvoices-1.0.1.dist-info/LICENSE
getmyinvoices-1.0.1.dist-info/METADATA
getmyinvoices-1.0.1.dist-info/WHEEL
getmyinvoices-1.0.1.dist-info/top_level.txt
getmyinvoices-1.0.1.dist-info/RECORD
